[
{"type":"header","version":"5.2.1","comment":"Export to JSON plugin for PHPMyAdmin"},
{"type":"database","name":"maintenance_infiguard"},
{"type":"table","name":"company","database":"maintenance_infiguard","data":
[
{"id":"1","type":"admin","company_administrator":"Marcos Rodriguez","company_name":"INFINIGUARD® GLOBAL","company_logo":"cdb04371-efd1-4380-a504-4b32652089751.jpg","profile_image":"cdb04371-efd1-4380-a504-4b3265208975.jpg","company_email":"maintenance@infiniguard.com","company_phone":"+1-858-284-7400","company_password":"369cd04b77250f4c38536b573acece18","status":"1","confirm_code":"23603","created_date":"2018-12-04 : 10:12:15","modify_date":"2024-02-22 : 07:02:42"},
{"id":"2","type":"normal","company_administrator":"Cesar Zamarripa","company_name":"INFINIGUARD Mexico","company_logo":"logo.png","profile_image":"logo1.png","company_email":"cesar@infiniguard.com","company_phone":"+52 (1) 81 1660 2007","company_password":"0aac23496816cbe4c339930e405440f1","status":"1","confirm_code":"62063","created_date":"2019-03-16 : 04:03:59","modify_date":"2024-03-13 : 11:03:57"},
{"id":"3","type":"normal","company_administrator":"Manuel Oquendo","company_name":"Space Cooling Puerto Rico","company_logo":"scprlogo.png","profile_image":"scprlogo1.png","company_email":"manuel.oquendo@spacecoolingpr.com","company_phone":"+1 (787) 604-9276","company_password":"96917805fd060e3766a9a1b834639d35","status":"1","confirm_code":null,"created_date":"2019-03-16 : 04:03:31","modify_date":"2021-03-09 : 08:03:33"},
{"id":"4","type":"normal","company_administrator":"Marcos Rodriguez","company_name":"Caribbean Energy Solutions LLC","company_logo":"CESHighRes3.png","profile_image":"images.jpg","company_email":"marcos@infiniguard.com","company_phone":"+1-858-284-7400","company_password":"065985de9a4b12f2a175c300a4f4641b","status":"1","confirm_code":"69689","created_date":"2019-03-25 : 01:03:17","modify_date":"2024-03-12 : 03:03:58"},
{"id":"5","type":"normal","company_administrator":"Timothy Baxley","company_name":"McCall's Supply, Inc.","company_logo":"mccallslogo.jpg","profile_image":"mccallslogo1.jpg","company_email":"tbaxley@mccallsinc.com","company_phone":"+1 (843) 933-5244","company_password":"252f76ee7303c2cc51224a8814f5a5a0","status":"1","confirm_code":null,"created_date":"2019-04-15 : 03:04:42","modify_date":"2022-04-22 : 09:04:41"},
{"id":"6","type":"normal","company_administrator":"Ron Bailey","company_name":"Total Comfort Solutions","company_logo":"totalcomfortsolutionslogo.jpg","profile_image":"totalcomfortsolutionslogo1.jpg","company_email":"ron.bailey@totalcomfortsolutions.com","company_phone":"+1 (843) 442-4282","company_password":"4d429d10f5a0a3fd48dd03da53061940","status":"1","confirm_code":null,"created_date":"2019-05-06 : 03:05:04","modify_date":"2022-04-22 : 09:04:30"},
{"id":"7","type":"normal","company_administrator":"Humberto Avila","company_name":"Trane Mexico","company_logo":"ScreenShot2021-01-25at74922AM.png","profile_image":"ScreenShot2021-01-25at74922AM1.png","company_email":"humberto.avila@tranetechnologies.com","company_phone":"+52 1 81 1707 1794","company_password":"d9f96c4ede798c307ea73c05199e291c","status":"1","confirm_code":null,"created_date":"2019-05-12 : 07:05:42","modify_date":"2021-01-25 : 03:01:41"},
{"id":"8","type":"normal","company_administrator":"Jatniel Vazquez","company_name":"Jayvee Air Conditioning, Inc.","company_logo":"ScreenShot2019-05-17at25329PM.png","profile_image":"ScreenShot2019-05-17at25329PM1.png","company_email":"jayveeac@live.com","company_phone":"+1 (787) 594-5863","company_password":"5fb4fe0fe1a3faed2d96dbd13b91c174","status":"1","confirm_code":null,"created_date":"2019-05-17 : 09:05:33","modify_date":"2022-04-22 : 09:04:00"},
{"id":"9","type":"normal","company_administrator":"Luis Ballesteros","company_name":"RCR Refrigeracion","company_logo":"download.png","profile_image":"download1.png","company_email":"lballesteros@rcr.com.mx","company_phone":"+52 662 496 9059","company_password":"39bf40086c13bb1032d892c82246f206","status":"1","confirm_code":null,"created_date":"2019-05-22 : 04:05:07","modify_date":"2021-03-31 : 03:03:13"},
{"id":"10","type":"normal","company_administrator":"Jim Gallagher","company_name":"Master Heating and Cooling","company_logo":"logo-pic.jpg","profile_image":"logo-pic1.jpg","company_email":"jimzdetailing@gmail.com","company_phone":"+1-252-305-3798","company_password":"c075f4a0f8a11acbad004f36eb3f93a3","status":"1","confirm_code":null,"created_date":"2019-05-22 : 04:05:53","modify_date":"2022-12-15 : 06:12:52"},
{"id":"11","type":"normal","company_administrator":"Pedro Muñiz","company_name":"Trane Puerto Rico","company_logo":"1200px-Trane_logosvg2.png","profile_image":"1200px-Trane_logosvg3.png","company_email":"pedro.muniz@trane.com","company_phone":"+1-787-587-8445","company_password":"d9891900f1edaeb5b8bf051d61addcdf","status":"1","confirm_code":null,"created_date":"2019-05-28 : 04:05:47","modify_date":"2022-04-22 : 09:04:48"},
{"id":"12","type":"normal","company_administrator":"Stephen Balk","company_name":"Mechanical Service Solutions","company_logo":"ScreenShot2019-06-03at21535PM.png","profile_image":"ScreenShot2019-06-03at21535PM1.png","company_email":"stephen@mechanicalservicesolutions.com","company_phone":"+1-757-617-8943","company_password":"d72d6b854fd84c5a380f393995166eb9","status":"1","confirm_code":null,"created_date":"2019-06-03 : 09:06:02","modify_date":"2022-04-22 : 09:04:32"},
{"id":"13","type":"normal","company_administrator":"Hector Perez","company_name":"Grupo Cemca","company_logo":"cemca.gif","profile_image":"cemca1.gif","company_email":"hectorperez@grupocemca.com","company_phone":"(809) 565-7397","company_password":"9b370b25fb7491067db1a4d252a12d17","status":"1","confirm_code":null,"created_date":"2019-06-12 : 02:06:21","modify_date":"2022-04-22 : 09:04:20"},
{"id":"14","type":"normal","company_administrator":"Olga de los Santos","company_name":"Odesa","company_logo":"ScreenShot2019-06-11at95305PM.png","profile_image":"ScreenShot2019-06-11at95305PM1.png","company_email":"odelossantos@odesa.do","company_phone":"+1 (809) 227-20-23","company_password":"38415162619ea08b3afeb3b729a6cfa3","status":"1","confirm_code":null,"created_date":"2019-06-12 : 02:06:49","modify_date":"2022-04-22 : 09:04:57"},
{"id":"15","type":"normal","company_administrator":"Steve Hill","company_name":"Beaufort Carolina Comfort","company_logo":"BCC_logo.png","profile_image":"BCC_logo1.png","company_email":"info@beaufortcarolinacomfort.com","company_phone":"+1 252-728-6943","company_password":"f0cf41b8c7a9354b1384a65291e94403","status":"1","confirm_code":null,"created_date":"2019-06-24 : 03:06:14","modify_date":"2022-04-22 : 09:04:12"},
{"id":"16","type":"normal","company_administrator":"Ben Dodge","company_name":"Tri-County Mechanical, Inc.","company_logo":"TCM_logo-HR1.png","profile_image":"TCM_logo-HR11.png","company_email":"info@tricountymechanicalinc.com","company_phone":"+1 843-773-2442","company_password":"9dafa49e7cc8d3c191c639fd59cd53cf","status":"1","confirm_code":null,"created_date":"2019-07-10 : 04:07:47","modify_date":"2022-04-22 : 09:04:08"},
{"id":"17","type":"normal","company_administrator":null,"company_name":"Edgardo Quintana HVAC","company_logo":"ScreenShot2019-07-23at94327AM.png","profile_image":"ScreenShot2019-07-23at94327AM1.png","company_email":"quintanaac@yahoo.com","company_phone":"+1 (787) 647-8900","company_password":"973a4ddd5be1826449e0ecf1f65f39e1","status":"0","confirm_code":null,"created_date":"2019-07-23 : 01:07:10","modify_date":"2023-05-01 : 08:05:42"},
{"id":"18","type":"normal","company_administrator":"Gabriel Molina","company_name":"Copper Group El Salvador","company_logo":"COPPERGROUPLOGOPNG.png","profile_image":"COPPERGROUPLOGOPNG1.png","company_email":"gabriel.molina@coppergroupint.com","company_phone":"+50379603909","company_password":"9a45e3002d059bd2fb4062ab8072bcbb","status":"1","confirm_code":null,"created_date":"2019-09-26 : 07:09:48","modify_date":"2022-04-22 : 09:04:06"},
{"id":"20","type":"normal","company_administrator":null,"company_name":null,"company_logo":"download21.png","profile_image":"download32.jpg","company_email":"r.taveras@core.com.do","company_phone":"+8093839383","company_password":"c5b8975f0dea1f80943752c0e85681d3","status":"0","confirm_code":null,"created_date":"2019-10-16 : 03:10:49","modify_date":"2024-03-26 : 09:03:37"},
{"id":"21","type":"normal","company_administrator":"Salvador Guerra","company_name":"Guerra Engineering","company_logo":"GEFINAL.png","profile_image":"GEFINAL1.png","company_email":"salvador@guerraengineering.com","company_phone":"+5016101705","company_password":"1d9791371a6f35cbfb756f6940fc837d","status":"1","confirm_code":null,"created_date":"2019-10-16 : 03:10:27","modify_date":"2022-04-22 : 09:04:47"},
{"id":"22","type":"normal","company_administrator":"Eduardo Velazquez","company_name":"Danfoss Guadalajara","company_logo":"1280px-Danfosssvg.png","profile_image":"1280px-Danfosssvg1.png","company_email":"danfoss_guadalajara@infiniguard.com","company_phone":"+5233","company_password":"feb50dca7bd7a1cad013d066e751fbe2","status":"1","confirm_code":null,"created_date":"2019-11-21 : 07:11:26","modify_date":"2022-11-10 : 06:11:49"},
{"id":"23","type":"normal","company_administrator":"Sean Hill","company_name":"Otis Air","company_logo":"Otis.png","profile_image":"Otis1.png","company_email":"sean.hill@otisair.ky","company_phone":"(345) 945-7167","company_password":"14bb9db1a22d1625b2e5fa2cd88f9209","status":"1","confirm_code":null,"created_date":"2019-12-16 : 06:12:36","modify_date":"2022-04-22 : 09:04:00"},
{"id":"24","type":"normal","company_administrator":"Jean Pierre Pujalt","company_name":"Cabo Frio","company_logo":"ScreenShot2020-01-10at110541AM.png","profile_image":"ScreenShot2020-01-10at110541AM1.png","company_email":"compras@cabofrio.com.mx","company_phone":"+52 (624) 588 6864","company_password":"11c9efa639a13c650cc4ccf081500383","status":"1","confirm_code":null,"created_date":"2020-01-10 : 07:01:23","modify_date":"2021-03-19 : 01:03:22"},
{"id":"25","type":"normal","company_administrator":null,"company_name":"Caribbean International Air Conditioning Services, Ltd.","company_logo":"image001.png","profile_image":"image0011.png","company_email":"aarenasg@ciacs.com","company_phone":"+(242) 356 4315","company_password":"82c614e8b665c8374c8759df50a4091b","status":"1","confirm_code":null,"created_date":"2020-01-23 : 04:01:43","modify_date":"2020-01-23 : 04:01:43"},
{"id":"26","type":"normal","company_administrator":"Alejandro Campos","company_name":"Oldach PR","company_logo":"logo-oldach-puerto-rico.png","profile_image":"logo-oldach-puerto-rico1.png","company_email":"alejandro.campos@oldachpr.com","company_phone":"+1-787-220-4623","company_password":"0b24e0827e4a9a0dd7d8dea839d42d6b","status":"1","confirm_code":null,"created_date":"2020-02-21 : 03:02:02","modify_date":"2022-01-18 : 07:01:45"},
{"id":"27","type":"normal","company_administrator":null,"company_name":"Espiaire","company_logo":"espiaire-logo.png","profile_image":"espiaire-logo1.png","company_email":"servicios@espiaire.com.mx","company_phone":"+52 998 112 3267","company_password":"fddf7f4e4befd3e419244ef949828efe","status":"1","confirm_code":null,"created_date":"2020-02-29 : 10:02:30","modify_date":"2020-02-29 : 10:02:30"},
{"id":"28","type":"normal","company_administrator":"Joussif Abdul-Hamid","company_name":"SimplAire","company_logo":"ScreenShot2020-03-03at113520AM.png","profile_image":"SimplAireLogo-Rectangle.jpg","company_email":"joussif.abdulhamid@simplaire.nl","company_phone":"+599 9 6602038","company_password":"c6f4cc0a73668ffb8873cf07c33ed0ae","status":"1","confirm_code":null,"created_date":"2020-03-03 : 03:03:00","modify_date":"2023-02-06 : 03:02:14"},
{"id":"29","type":"normal","company_administrator":"Daniel Vazquez","company_name":"Clima Ideal S.A.","company_logo":"download4.png","profile_image":"download5.png","company_email":"dvazquez@climaideal.com","company_phone":"4404-9100","company_password":"9cb93d481af609ea89e4122c29ef280a","status":"1","confirm_code":null,"created_date":"2020-03-04 : 08:03:45","modify_date":"2022-04-22 : 09:04:50"},
{"id":"30","type":"normal","company_administrator":"Hanry Brenes","company_name":"Sistemas Ecologicos Confortables, S.A.","company_logo":"download.jpeg","profile_image":"download1.jpeg","company_email":"infiniguard@econfortsa.com","company_phone":"2269 0050","company_password":"68434e0594495b632fa4cfe9ea884283","status":"1","confirm_code":null,"created_date":"2020-03-05 : 08:03:55","modify_date":"2022-04-22 : 09:04:07"},
{"id":"31","type":"normal","company_administrator":"Rohan Ranmath","company_name":"Qualitech \/ Premier Air Conditioning and Refrigeration Company Limited","company_logo":"premiersign2010a.jpg","profile_image":"premiersign2010a1.jpg","company_email":"rohanramnath_7@yahoo.com","company_phone":"+18687881154","company_password":"128385237a5dbada59faec1b54716643","status":"1","confirm_code":null,"created_date":"2020-03-11 : 07:03:35","modify_date":"2022-04-22 : 09:04:39"},
{"id":"32","type":"normal","company_administrator":"Darrell Cheng","company_name":"New Tech","company_logo":"newtechlogo2018zwartebalk.png","profile_image":"newtechlogo2018zwartebalk1.png","company_email":"darrell.chengajune@newtech.sr","company_phone":"+597 8237280","company_password":"cf2a9f4538c4567b8d881006fdeffe07","status":"1","confirm_code":null,"created_date":"2020-03-12 : 03:03:36","modify_date":"2022-04-22 : 09:04:14"},
{"id":"33","type":"normal","company_administrator":"Chad Collins","company_name":"Specialty Coils LLC","company_logo":"specailty_coils_light.jpg","profile_image":"specailty_coils_light1.jpg","company_email":"chad.collins@specialtycoils.com","company_phone":"+1-903-212-2645; X12","company_password":"60924a2589ebd4b8d50959c0df79a4c8","status":"1","confirm_code":null,"created_date":"2020-03-18 : 05:03:36","modify_date":"2022-04-22 : 09:04:14"},
{"id":"34","type":"normal","company_administrator":"Jennifer Snider-Harvey","company_name":"Holy City HVAC","company_logo":"hchvac1.png","profile_image":"1552357.jpg","company_email":"jen@holycityhvac.com","company_phone":"+1-843-990-2425","company_password":"6f41f8614fe309793cf3d2bd20dcbc73","status":"1","confirm_code":null,"created_date":"2020-05-28 : 04:05:36","modify_date":"2021-02-01 : 03:02:39"},
{"id":"35","type":"normal","company_administrator":"Casey Landry","company_name":"Adapt Concepts LLC","company_logo":"Adapt-Main-Logo.png","profile_image":"Adapt-Main-Logo1.png","company_email":"casey@adaptconceptsllc.com","company_phone":"+1-337-408-8202","company_password":"2fe3a45ef84131263e38965d36b6fc0d","status":"1","confirm_code":null,"created_date":"2020-06-03 : 01:06:15","modify_date":"2022-04-22 : 09:04:07"},
{"id":"39","type":"normal","company_administrator":"Javier Montero","company_name":"INFINIGUARD Dominicana","company_logo":"INFINIGUARDAppIcon3.png","profile_image":"IMG_0554.JPG","company_email":"javier@infiniguard.com","company_phone":"+18492548444","company_password":"827ccb0eea8a706c4c34a16891f84e7b","status":"1","confirm_code":null,"created_date":"2020-07-29 : 01:07:57","modify_date":"2023-01-23 : 09:01:39"},
{"id":"40","type":"normal","company_administrator":"Carlos Mario Castillo","company_name":"CC Aires","company_logo":"logo-ccaires-200x90.png","profile_image":"logo-ccaires-200x901.png","company_email":"carlos@ccaires.com","company_phone":"+57-320-507-5641","company_password":"81dc9bdb52d04dc20036dbd8313ed055","status":"1","confirm_code":null,"created_date":"2020-08-25 : 03:08:14","modify_date":"2020-08-25 : 03:08:14"},
{"id":"43","type":"normal","company_administrator":"Robbio Di Vecchia","company_name":"Aruba Climate Control NV","company_logo":"acc-logo.png","profile_image":"acc-logo1.png","company_email":"robbiodivecchia@hotmail.com","company_phone":"+297-593-0297","company_password":"81dc9bdb52d04dc20036dbd8313ed055","status":"1","confirm_code":null,"created_date":"2020-12-17 : 02:12:14","modify_date":"2020-12-17 : 02:12:14"},
{"id":"45","type":"normal","company_administrator":"Pamela Pineda","company_name":"Grupo Ayre","company_logo":"grupoayre.png","profile_image":"grupoayre1.png","company_email":"ppineda@grupoayre.com","company_phone":"+504 2504-2121","company_password":"827ccb0eea8a706c4c34a16891f84e7b","status":"1","confirm_code":null,"created_date":"2021-03-22 : 03:03:31","modify_date":"2021-03-22 : 03:03:31"},
{"id":"47","type":"normal","company_administrator":"Miguel Hurtado","company_name":"INFINIGUARD Miami LLC","company_logo":"INFINIGUARDHighRes.jpg","profile_image":"INFINIGUARDHighRes1.jpg","company_email":"miami@infiniguard.com","company_phone":"8582847400","company_password":"fee43618da81724b55de9c2f1dc4a2a8","status":"1","confirm_code":null,"created_date":"2021-07-21 : 08:07:45","modify_date":"2021-07-21 : 08:07:45"},
{"id":"48","type":"normal","company_administrator":"Hiram Moreno","company_name":"Hiram Moreno","company_logo":"blank.JPG","profile_image":"blank1.JPG","company_email":"hiram.moreno822@gmail.com","company_phone":"1234567890","company_password":"e10adc3949ba59abbe56e057f20f883e","status":"1","confirm_code":null,"created_date":"2021-09-09 : 12:09:17","modify_date":"2021-09-09 : 12:09:17"},
{"id":"49","type":"normal","company_administrator":"Chris Hughes","company_name":"Bailey Heating and Controls","company_logo":"blank2.JPG","profile_image":"blank3.JPG","company_email":"chris@baileyheating.com","company_phone":"864-963-1652","company_password":"81dc9bdb52d04dc20036dbd8313ed055","status":"1","confirm_code":null,"created_date":"2021-09-14 : 07:09:35","modify_date":"2021-09-14 : 07:09:35"},
{"id":"50","type":"normal","company_administrator":"Michael Herrmann","company_name":"H&H Coil Coating LLC","company_logo":"blank4.JPG","profile_image":"blank5.JPG","company_email":"hhcoilcoatingllc@gmail.com","company_phone":"0000000000","company_password":"81dc9bdb52d04dc20036dbd8313ed055","status":"1","confirm_code":null,"created_date":"2021-09-22 : 02:09:59","modify_date":"2021-09-22 : 02:09:59"},
{"id":"51","type":"normal","company_administrator":"Andres Brito","company_name":"HVAC Clima Servicio y Controles Iberia, S.L.","company_logo":"blank6.JPG","profile_image":"blank7.JPG","company_email":"Andres.Brito@carrier.com","company_phone":"+ 34 660 065 344","company_password":"81dc9bdb52d04dc20036dbd8313ed055","status":"1","confirm_code":null,"created_date":"2022-02-14 : 05:02:46","modify_date":"2022-02-14 : 05:02:46"},
{"id":"52","type":"normal","company_administrator":"Yisrael Guttentag","company_name":"Trane Israel","company_logo":"blank8.JPG","profile_image":"blank9.JPG","company_email":"Yisrael_Guttentag@trane.com","company_phone":"+972545933993","company_password":"81dc9bdb52d04dc20036dbd8313ed055","status":"1","confirm_code":null,"created_date":"2022-08-22 : 02:08:50","modify_date":"2022-08-22 : 02:08:50"},
{"id":"53","type":"normal","company_administrator":"Marcelo Cormick","company_name":"Hilton Cancun","company_logo":"blank10.JPG","profile_image":"blank11.JPG","company_email":"marcelo.cormick@hilton.com","company_phone":"(305) 790-6647","company_password":"81dc9bdb52d04dc20036dbd8313ed055","status":"1","confirm_code":null,"created_date":"2022-08-22 : 08:08:30","modify_date":"2022-08-22 : 08:08:30"},
{"id":"54","type":"normal","company_administrator":"Stephen Southerland","company_name":"Coastline Coating Services LLC","company_logo":"blank12.JPG","profile_image":"blank13.JPG","company_email":"stevesouth35@gmail.com","company_phone":"910-622-0013","company_password":"81dc9bdb52d04dc20036dbd8313ed055","status":"1","confirm_code":null,"created_date":"2022-08-30 : 03:08:18","modify_date":"2022-08-31 : 06:08:00"},
{"id":"55","type":"normal","company_administrator":"Jordan White","company_name":"Carteret Heating and Cooling","company_logo":"blank12.JPG","profile_image":"blank13.JPG","company_email":"jordan@carteretheatingandcooling.com","company_phone":"252-393-7712","company_password":"81dc9bdb52d04dc20036dbd8313ed055","status":"1","confirm_code":null,"created_date":"2022-09-07 : 07:09:38","modify_date":"2022-09-07 : 07:09:38"},
{"id":"56","type":"normal","company_administrator":"developer infiniguard","company_name":"developer infiniguard","company_logo":"3BF4C0DD-3C07-418B-8E7A-C792809F2B042.jpeg","profile_image":"3BF4C0DD-3C07-418B-8E7A-C792809F2B041.jpeg","company_email":"developer@infiniguard.com","company_phone":"+1-858-284-7400","company_password":"daa7216240a33907d923c3fa5d4dc0b9","status":"1","confirm_code":"14956","created_date":"2022-10-18 : 11:10:23","modify_date":"2022-10-31 : 05:10:11"},
{"id":"57","type":"normal","company_administrator":"George Lee","company_name":"Quantum Technologies","company_logo":"blank14.JPG","profile_image":"blank15.JPG","company_email":"george.lee@quantum-technologies-inc.com","company_phone":"843-442-5499","company_password":"81dc9bdb52d04dc20036dbd8313ed055","status":"1","confirm_code":null,"created_date":"2022-11-01 : 06:11:01","modify_date":"2022-11-01 : 06:11:01"},
{"id":"58","type":"normal","company_administrator":"Harry Hinkle","company_name":"Coastal Coil Coatings","company_logo":"blank16.JPG","profile_image":"blank17.JPG","company_email":"coastalindustrialcoatings@gmail.com","company_phone":"570-436-7699","company_password":"81dc9bdb52d04dc20036dbd8313ed055","status":"1","confirm_code":null,"created_date":"2022-11-09 : 01:11:22","modify_date":"2022-11-09 : 01:11:22"},
{"id":"59","type":"normal","company_administrator":"Test Company Administrator","company_name":"Test Company","company_logo":"logo.png","profile_image":"logo1.png","company_email":"testemail@testcompany.com","company_phone":"1234567","company_password":"6ac9c446a8f6232048e8e0348a8d8dfd","status":"1","confirm_code":"24500","created_date":"2019-03-16 : 04:03:59","modify_date":"2023-04-18 : 08:04:40"},
{"id":"60","type":"normal","company_administrator":"Test Admin","company_name":"Test Company","company_logo":"new-logo3.png","profile_image":"new-logo4.png","company_email":"test230406@infiniguard.com","company_phone":"123456789","company_password":"098f6bcd4621d373cade4e832627b4f6","status":"1","confirm_code":null,"created_date":"2022-12-27 : 09:12:28","modify_date":"2024-03-29 : 07:03:56"},
{"id":"61","type":"normal","company_administrator":"Robert Taylor","company_name":"R&K Heating and Cooling","company_logo":"Infiniguard-Mascota-V2.png","profile_image":"Infiniguard-Mascota-V21.png","company_email":"rkheatingandcooling2012@gmail.com","company_phone":"252-917-3258","company_password":"827ccb0eea8a706c4c34a16891f84e7b","status":"1","confirm_code":null,"created_date":"2023-01-18 : 02:01:25","modify_date":"2023-01-18 : 02:01:25"},
{"id":"62","type":"normal","company_administrator":"Victor TJ","company_name":"Safario","company_logo":"blank18.JPG","profile_image":"blank19.JPG","company_email":"victor@safario.com","company_phone":"055 1072403","company_password":"4068b48d002e281a3164d262778a6a77","status":"1","confirm_code":null,"created_date":"2023-02-16 : 12:02:41","modify_date":"2023-09-19 : 02:09:09"},
{"id":"63","type":"normal","company_administrator":"Brian O'Connell","company_name":"Armor Coat","company_logo":"blank20.JPG","profile_image":"blank21.JPG","company_email":"brian@nccomfortsystems.com","company_phone":"910-358-3987","company_password":"81dc9bdb52d04dc20036dbd8313ed055","status":"1","confirm_code":null,"created_date":"2023-03-03 : 02:03:53","modify_date":"2023-03-03 : 02:03:53"},
{"id":"64","type":"normal","company_administrator":"Test Company Administrator","company_name":"Test Company code","company_logo":"logo.png","profile_image":"logo1.png","company_email":"codecoretesting@gmail.com","company_phone":"1234567","company_password":"8ab829bc684ce48a09120cb14095d079","status":"1","confirm_code":"95755","created_date":"2019-03-16 : 04:03:59","modify_date":"2024-03-26 : 07:03:28"},
{"id":"65","type":"normal","company_administrator":"Test Admin","company_name":"TT","company_logo":"a7982d9c6c957b9309b210be16b52634.jpg","profile_image":"a7982d9c6c957b9309b210be16b526341.jpg","company_email":"codeasdasdasdasdasdcoretesting@gmail.com","company_phone":"3434343","company_password":"2f803268a6367d0943978eb5f84cc62e","status":"1","confirm_code":null,"created_date":"2023-05-09 : 10:05:01","modify_date":"2023-05-09 : 10:05:01"},
{"id":"66","type":"normal","company_administrator":"Rolando Salvo","company_name":"Q Club Hotels LLC","company_logo":"download.jpg","profile_image":"download1.jpg","company_email":"rolando.salvo@hilton.com","company_phone":"954.882-9609","company_password":"81dc9bdb52d04dc20036dbd8313ed055","status":"1","confirm_code":null,"created_date":"2023-05-17 : 07:05:12","modify_date":"2023-05-17 : 07:05:12"},
{"id":"67","type":"normal","company_administrator":"Dennis Patram","company_name":"Gideon Heating and Air Conditioning INC","company_logo":"BLANK.png","profile_image":"BLANK1.png","company_email":"dennis@gideonhvac.com","company_phone":"000-000-0000","company_password":"81dc9bdb52d04dc20036dbd8313ed055","status":"1","confirm_code":null,"created_date":"2023-06-09 : 02:06:44","modify_date":"2023-06-09 : 02:06:44"},
{"id":"68","type":"normal","company_administrator":"Logan Sosa","company_name":"Comfort Heating and Cooling Inc.","company_logo":"BLANK2.png","profile_image":"BLANK3.png","company_email":"comfortcontractors@gmail.com","company_phone":"910-389--8461","company_password":"81dc9bdb52d04dc20036dbd8313ed055","status":"1","confirm_code":null,"created_date":"2023-06-19 : 06:06:28","modify_date":"2023-06-19 : 06:06:28"},
{"id":"69","type":"normal","company_administrator":"Martin Robles","company_name":"Fideicomiso LITIBU Operador CIB\/3222","company_logo":"BLANK4.png","profile_image":"BLANK5.png","company_email":"Martin.Robles@conradhotels.com","company_phone":"+52 322 138 8502","company_password":"81dc9bdb52d04dc20036dbd8313ed055","status":"1","confirm_code":null,"created_date":"2023-06-21 : 03:06:42","modify_date":"2023-06-21 : 03:06:42"},
{"id":"70","type":"normal","company_administrator":"Cristobal Ortega","company_name":"Waldorf Astoria Los Cabos Pedregal","company_logo":"BLANK6.png","profile_image":"BLANK7.png","company_email":"cristobal.ortega@waldorfastoria.com","company_phone":"+52 624 129 9710","company_password":"81dc9bdb52d04dc20036dbd8313ed055","status":"1","confirm_code":null,"created_date":"2023-06-26 : 07:06:22","modify_date":"2023-06-26 : 07:06:22"},
{"id":"71","type":"normal","company_administrator":"Donald Pogue","company_name":"Island Mechanical","company_logo":"BLANK8.png","profile_image":"BLANK9.png","company_email":"islandmech@gmail.com","company_phone":"+1 678 494 4863","company_password":"81dc9bdb52d04dc20036dbd8313ed055","status":"1","confirm_code":null,"created_date":"2023-07-05 : 06:07:40","modify_date":"2023-07-05 : 06:07:40"},
{"id":"72","type":"normal","company_administrator":"Bryan Montgomery","company_name":"Solaire TCI","company_logo":"BLANK10.png","profile_image":"BLANK11.png","company_email":"bryan@solairetci.com","company_phone":"000 000 0000","company_password":"81dc9bdb52d04dc20036dbd8313ed055","status":"1","confirm_code":null,"created_date":"2023-07-05 : 06:07:33","modify_date":"2023-07-05 : 06:07:33"},
{"id":"73","type":"normal","company_administrator":"Stavros Scicluna","company_name":"Panta Contracting Limited","company_logo":"BLANK12.png","profile_image":"BLANK13.png","company_email":"stavrosscicluna@panta.mt","company_phone":"+356 9949 2315","company_password":"81dc9bdb52d04dc20036dbd8313ed055","status":"1","confirm_code":null,"created_date":"2023-07-11 : 05:07:43","modify_date":"2023-07-11 : 05:07:43"},
{"id":"74","type":"normal","company_administrator":"Diego Rivera","company_name":"Centro Climatico","company_logo":"BLANK14.png","profile_image":"BLANK15.png","company_email":"centroclimaticocr@gmail.com","company_phone":"+506-8701-8801","company_password":"81dc9bdb52d04dc20036dbd8313ed055","status":"1","confirm_code":null,"created_date":"2023-12-05 : 04:12:41","modify_date":"2023-12-05 : 04:12:41"},
{"id":"75","type":"normal","company_administrator":"Pedro Harris","company_name":"American Parts Company, S.A.","company_logo":"BLANK16.png","profile_image":"BLANK17.png","company_email":"pedroharris@airsolutionspty.com","company_phone":"+507 6672 7877","company_password":"81dc9bdb52d04dc20036dbd8313ed055","status":"1","confirm_code":null,"created_date":"2024-03-21 : 05:03:59","modify_date":"2024-03-21 : 05:03:59"},
{"id":"76","type":"admin","company_administrator":"Administrator Name","company_name":"Infiniguard","company_logo":"logo_image.jpg","profile_image":"profile_image.jpg","company_email":"infiniguard@example.com","company_phone":"123456789","company_password":"$2y$12$5e\/8EKFMWEJX\/MbnSRDyW.Zar3sy8P5Bbg7LScFo\/EpI3Lrq7F5Fq","status":"1","confirm_code":null,"created_date":"2024-04-04 00:00:00","modify_date":"2024-04-04 00:00:00"}
]
}
]
